eisenradio/__init__.py
eisenradio/cmd.py
eisenradio/db.py
eisenradio/gui.py
eisenradio/py.typed
eisenradio/schema.sql
eisenradio/wsgi.py
eisenradio/api/__init__.py
eisenradio/eisenhome/__init__.py
eisenradio/eisenhome/eishome.py
eisenradio/eisenhome/routes.py
eisenradio/eisenhome/watchdog.py
eisenradio/eisenhome/bp_home_static/favicon.ico
eisenradio/eisenhome/bp_home_static/css/style.css
eisenradio/eisenhome/bp_home_static/images/eisenposter950.png
eisenradio/eisenhome/bp_home_static/images/svgImagesSymbol.svg
eisenradio/eisenhome/bp_home_static/jquery/jquery-3.6.0.min.js
eisenradio/eisenhome/bp_home_static/js/analyzer.js
eisenradio/eisenhome/bp_home_static/js/constants.js
eisenradio/eisenhome/bp_home_static/js/index.js
eisenradio/eisenhome/bp_home_static/js/playlist.js
eisenradio/eisenhome/bp_home_static/js/svg-airPlanes.js
eisenradio/eisenhome/bp_home_static/js/svg-balloons.js
eisenradio/eisenhome/bp_home_static/js/svg-birds.js
eisenradio/eisenhome/bp_home_static/js/svg-cloudsIce.js
eisenradio/eisenhome/bp_home_static/js/svg-foreBackGround.js
eisenradio/eisenhome/bp_home_static/js/svg-frontMan.js
eisenradio/eisenhome/bp_home_static/js/svg-main.js
eisenradio/eisenhome/bp_home_static/js/svg-manage.js
eisenradio/eisenhome/bp_home_static/js/svg-parachuteDrop.js
eisenradio/eisenhome/bp_home_static/js/svg-satellites.js
eisenradio/eisenhome/bp_home_static/js/svg-screwHeads.js
eisenradio/eisenhome/bp_home_static/js/svg-seaWaves.js
eisenradio/eisenhome/bp_home_static/js/svg-speaker.js
eisenradio/eisenhome/bp_home_static/js/svg-sprite.js
eisenradio/eisenhome/bp_home_static/js/svg-teslaCoils.js
eisenradio/eisenhome/bp_home_static/js/svg-toCanvas.js
eisenradio/eisenhome/bp_home_static/js/svg-ufo.js
eisenradio/eisenhome/bp_home_static/js/svg-utils.js
eisenradio/eisenhome/bp_home_static/js/theme-arctic.js
eisenradio/eisenhome/bp_home_static/js/theme-cut.js
eisenradio/eisenhome/bp_home_static/js/theme-sunset.js
eisenradio/eisenhome/bp_home_templates/bp_home_base.html
eisenradio-2.4.2.dist-info/LICENSE.rst
eisenradio-2.4.2.dist-info/METADATA
eisenradio-2.4.2.dist-info/WHEEL
eisenradio-2.4.2.dist-info/top_level.txt
eisenradio-2.4.2.dist-info/zip-safe
eisenradio-2.4.2.dist-info/RECORD
