Metadata-Version: 2.1
Name: eisenradio
Version: 2.4.2
Summary: Play radio. Style your App.
Home-page: https://github.com/44xtc44
Author: René Horn
Author-email: rene_horn@gmx.net
License: MIT
Platform: UNKNOWN
Classifier: Programming Language :: Python :: 3
Classifier: License :: OSI Approved :: MIT License
Classifier: Operating System :: OS Independent
Classifier: Development Status :: 5 - Production/Stable
Classifier: Topic :: Multimedia :: Sound/Audio :: Capture/Recording
Requires-Python: >=3.8
License-File: LICENSE.rst
Requires-Dist: aacrepair
Requires-Dist: ghettorecorder (==2.4.7)
Requires-Dist: flask (>=2.3.2)
Requires-Dist: Werkzeug (>=2.2.3)
Requires-Dist: pytest (>=6.2.5)
Requires-Dist: python-dotenv (>=0.19.2)
Requires-Dist: waitress
